odoo9_addon_crm_phonecall_planner-9.0.1.0.0-py2.7-nspkg.pth
odoo9_addon_crm_phonecall_planner-9.0.1.0.0.dist-info/DESCRIPTION.rst
odoo9_addon_crm_phonecall_planner-9.0.1.0.0.dist-info/METADATA
odoo9_addon_crm_phonecall_planner-9.0.1.0.0.dist-info/RECORD
odoo9_addon_crm_phonecall_planner-9.0.1.0.0.dist-info/WHEEL
odoo9_addon_crm_phonecall_planner-9.0.1.0.0.dist-info/metadata.json
odoo9_addon_crm_phonecall_planner-9.0.1.0.0.dist-info/namespace_packages.txt
odoo9_addon_crm_phonecall_planner-9.0.1.0.0.dist-info/top_level.txt
odoo_addons/crm_phonecall_planner/README.rst
odoo_addons/crm_phonecall_planner/__init__.py
odoo_addons/crm_phonecall_planner/__openerp__.py
odoo_addons/crm_phonecall_planner/i18n/es.po
odoo_addons/crm_phonecall_planner/static/description/icon.png
odoo_addons/crm_phonecall_planner/tests/__init__.py
odoo_addons/crm_phonecall_planner/tests/test_planner.py
odoo_addons/crm_phonecall_planner/wizards/__init__.py
odoo_addons/crm_phonecall_planner/wizards/crm_phonecall_planner.py
odoo_addons/crm_phonecall_planner/wizards/crm_phonecall_planner_view.xml
